pyyadisk/__init__.py
pyyadisk/config.py
pyyadisk/helpers.py
pyyadisk/yandexdisk.py
pyyadisk-0.1.3.dist-info/LICENSE
pyyadisk-0.1.3.dist-info/METADATA
pyyadisk-0.1.3.dist-info/WHEEL
pyyadisk-0.1.3.dist-info/top_level.txt
pyyadisk-0.1.3.dist-info/RECORD
