Metadata-Version: 2.1
Name: pyyadisk
Version: 0.1.3
Summary: PyYaDisk is a small wrapper over Yandex Disk Rest API V1
Home-page: https://github.com/ndrwpvlv/pyyadisk
Author: Andrei S. Pavlov
Author-email: andy_pavlov@outlook.com
License: MIT
Download-URL: https://github.com/ndrwpvlv/pyyadisk/archive/refs/tags/0.1.2.tar.gz
Keywords: Yandex,Yandex Disk,Yandex Disk REST API
Platform: UNKNOWN
Classifier: Programming Language :: Python :: 3.6
Classifier: Programming Language :: Python :: 3.7
Classifier: Programming Language :: Python :: 3.8
Classifier: Programming Language :: Python :: 3.9
Classifier: Operating System :: OS Independent
Classifier: License :: OSI Approved :: MIT License
License-File: LICENSE
Requires-Dist: requests (==2.26.0)
